retarus/fax/_async.py
retarus/fax/client.py
retarus/fax/model.py
retarus/fax/sync.py
retarus/fax_in_poll/_async.py
retarus/fax_in_poll/client.py
retarus/fax_in_poll/model.py
retarus/fax_in_poll/sync.py
retarus_fax-1.0.1.dist-info/LICENSE
retarus_fax-1.0.1.dist-info/METADATA
retarus_fax-1.0.1.dist-info/WHEEL
retarus_fax-1.0.1.dist-info/top_level.txt
retarus_fax-1.0.1.dist-info/RECORD
