Metadata-Version: 2.1
Name: retarus-fax
Version: 1.0.1
Author-email: Retarus GmbH <Developers@retarus.com>
License: Apache License
Project-URL: repository, https://github.com/retarus/retarus-python-fax
Project-URL: Documentation, https://developers.retarus.com/
Keywords: retarus,fax,cloud
Requires-Python: >=3.8
License-File: LICENSE
Requires-Dist: retarus-common (==0.1.2)
Requires-Dist: pytest-dependency (==0.5.1)
Requires-Dist: pytest (==7.2.0)
Requires-Dist: aiohttp
Requires-Dist: aiohttp-retry
Requires-Dist: pydantic
Requires-Dist: pytest-asyncio
Requires-Dist: requests
